{
  "name": "WPC COIN",
  "logoURI": "https://raw.githubusercontent.com/1769586104/token/main/logo.png",
  "keywords": [
      "WPC",
      "wpc"
    ],
    "timestamp": "2020-09-01T01:40:34.305Z",
    "tokens": [
      {
      "chainId": 1,
      "address": "0x6b14a4d7a561b924c76e8a356727a5dccbdfb38f",
      "name": "World Population Coin",
      "symbol": "WPC",
      "decimals": 18,
      "logoURI": "https://raw.githubusercontent.com/1769586104/token/main/logo.png"
      }
    ],
    "version": {
      "major": 1,
      "minor": 0,
      "patch": 0
    }
}
